{
  "items": [
    {
      "id": 1,
      "name": "Air Jordan 1",
      "style": "Lifestyle",
      "description": "Description for Item 1",
      "price": 300
    },
    {
      "id": 2,
      "name": "Air Force 1",
      "style": "Lifestyle",
      "description": "Description for Item 2",
      "price": 150
    },
    {
      "id": 3,
      "name": "Bape Sta",
      "style": "Hypebeast",
      "description": "Description for Item 3",
      "price": 500 
    },
    {
      "id": 4,
      "name": "Kobe 8",
      "style": "Basketball",
      "description": "Description for Item 4",
      "price": 900
    },
    {
      "id": 5,
      "name": "Yeezy Boost",
      "style": "Hypebeast",
      "description": "Description for Item 4",
      "price": 400
    },
    {
      "id": 6,
      "name": "Ramone Highs",
      "style": "Lifestyle",
      "description": "Baby, I'm the fashion demon",
      "price": 600
    },
    {
      "id": 7,
      "name": "Foam Runners",
      "style": "Running",
      "description": "Baby, I'm the fashion demon",
      "price": 250
    }
  ]
}

